gpt_token_tracker/__init__.py
gpt_token_tracker/__version__.py
gpt_token_tracker/models.py
gpt_token_tracker/pricing.py
gpt_token_tracker/pricing_anthropic.py
gpt_token_tracker/pricing_gemini.py
gpt_token_tracker/pricing_timed.py
gpt_token_tracker/token_logger.py
gpt_token_tracker/writers/__init__.py
gpt_token_tracker/writers/csv_writer.py
gpt_token_tracker/writers/log_writer.py
gpt_token_tracker/writers/types.py
gpt_token_tracker/writers/utils.py
gpt_token_tracker-0.5.0.dist-info/METADATA
gpt_token_tracker-0.5.0.dist-info/WHEEL
gpt_token_tracker-0.5.0.dist-info/top_level.txt
gpt_token_tracker-0.5.0.dist-info/RECORD
