Metadata-Version: 2.4
Name: gpt-token-tracker
Version: 0.5.0
Summary: Token usage and cost tracking for OpenAI responses (another AI providers in future)
Requires-Python: >=3.11
Requires-Dist: openai
Requires-Dist: google-genai
Requires-Dist: anthropic
Requires-Dist: pydantic>=2.0
